[
  {
    "clip_index": 1,
    "source_path": "/Volumes/@Basic/Muzyka/Soulseek Downloads/Meshuggah - obZen - 03 - Bleed.flac",
    "start_beat": 0,
    "end_beat": 59,
    "source_start_sec": 0.0,
    "source_end_sec": 36.357460317460315,
    "timeline_start_sec": 0.0,
    "timeline_end_sec": 36.357460317460315,
    "duration_sec": 36.357460317460315,
    "fade_in_sec": 0.0,
    "fade_out_sec": 0.0784126984126984,
    "overlap_before_sec": 0.0,
    "overlap_after_sec": 0.0784126984126984,
    "gap_after_sec": 0.0
  },
  {
    "clip_index": 2,
    "source_path": "/Volumes/@Basic/Muzyka/Soulseek Downloads/Meshuggah - obZen - 03 - Bleed.flac",
    "start_beat": 91,
    "end_beat": 114,
    "source_start_sec": 49.87591836734694,
    "source_end_sec": 60.0,
    "timeline_start_sec": 36.27904761904762,
    "timeline_end_sec": 46.403129251700676,
    "duration_sec": 10.124081632653061,
    "fade_in_sec": 0.0784126984126984,
    "fade_out_sec": 0.0,
    "overlap_before_sec": 0.0784126984126984,
    "overlap_after_sec": 0.0,
    "gap_after_sec": 0.0
  }
]