[
  {
    "clip_index": 1,
    "source_path": "/Volumes/@Basic/Muzyka/Soulseek Downloads/0104 - Iron (acoustic).flac",
    "start_beat": 0,
    "end_beat": 14,
    "source_start_sec": 0.0,
    "source_end_sec": 7.078140589569161,
    "timeline_start_sec": 0.0,
    "timeline_end_sec": 7.078140589569161,
    "duration_sec": 7.078140589569161,
    "fade_in_sec": 0.0,
    "fade_out_sec": 0.07024943310657597,
    "overlap_before_sec": 0.0,
    "overlap_after_sec": 0.07024943310657597,
    "gap_after_sec": 0.0
  },
  {
    "clip_index": 2,
    "source_path": "/Volumes/@Basic/Muzyka/Soulseek Downloads/0104 - Iron (acoustic).flac",
    "start_beat": 103,
    "end_beat": 127,
    "source_start_sec": 48.35995464852608,
    "source_end_sec": 60.0,
    "timeline_start_sec": 7.007891156462585,
    "timeline_end_sec": 18.647936507936507,
    "duration_sec": 11.640045351473923,
    "fade_in_sec": 0.07024943310657597,
    "fade_out_sec": 0.0,
    "overlap_before_sec": 0.07024943310657597,
    "overlap_after_sec": 0.0,
    "gap_after_sec": 0.0
  }
]